[
  {
    "id": "annomi-alcohol-minimizing-1",
    "source": "annomi",
    "clientGroup": "adult",
    "issueTags": ["alcohol", "ambivalence", "stress"],
    "clientUtterance": "I drink at home to unwind. It is not like I am getting into trouble.",
    "workerMove": "Open exploration of drinking pattern and reasons for drinking.",
    "affect": "defensive",
    "riskSignals": [],
    "resistanceType": "minimizing",
    "changeTalk": [],
    "disclosureDepth": 1,
    "quality": "approved",
    "licenseNote": "Seed abstraction from MI corpus pattern; not copied raw text."
  },
  {
    "id": "annomi-alcohol-ambivalence-1",
    "source": "annomi",
    "clientGroup": "adult",
    "issueTags": ["alcohol", "depression", "sleep"],
    "clientUtterance": "I do feel worse the morning after, but I also do not know what else helps me shut down at night.",
    "workerMove": "Reflective listening about both relief and costs.",
    "affect": "reflective",
    "riskSignals": ["depression worsening"],
    "resistanceType": "ambivalence",
    "changeTalk": ["recognizing cost", "reason to reduce"],
    "disclosureDepth": 3,
    "quality": "approved",
    "licenseNote": "Seed abstraction from MI corpus pattern; not copied raw text."
  },
  {
    "id": "annomi-alcohol-plan-1",
    "source": "annomi",
    "clientGroup": "adult",
    "issueTags": ["alcohol", "planning", "support"],
    "clientUtterance": "Maybe I could keep less wine at home and see if two nights are different.",
    "workerMove": "Affirm autonomy and ask for a concrete next step.",
    "affect": "reflective",
    "riskSignals": [],
    "resistanceType": "ambivalence",
    "changeTalk": ["ability", "commitment", "small step"],
    "disclosureDepth": 4,
    "quality": "approved",
    "licenseNote": "Seed abstraction from MI corpus pattern; not copied raw text."
  },
  {
    "id": "student-bullying-avoidance-1",
    "source": "student_mh_en",
    "clientGroup": "student",
    "issueTags": ["bullying", "school", "isolation"],
    "clientUtterance": "Lunch is just awkward now, so I go somewhere else and wait until class starts.",
    "workerMove": "Ask what changed with peers without forcing details.",
    "affect": "ashamed",
    "riskSignals": ["social isolation"],
    "resistanceType": "avoidance",
    "changeTalk": [],
    "disclosureDepth": 2,
    "quality": "approved",
    "licenseNote": "Seed abstraction from student mental-health corpus pattern; not copied raw text."
  },
  {
    "id": "student-bullying-group-chat-1",
    "source": "student_mh_en",
    "clientGroup": "student",
    "issueTags": ["bullying", "peer conflict", "shame"],
    "clientUtterance": "They removed me from the chat and I keep thinking screenshots are going around.",
    "workerMove": "Validate embarrassment and ask about safety at school.",
    "affect": "ashamed",
    "riskSignals": ["bullying escalation", "social isolation"],
    "resistanceType": "shame",
    "changeTalk": ["wants adult understanding"],
    "disclosureDepth": 3,
    "quality": "approved",
    "licenseNote": "Seed abstraction from student mental-health corpus pattern; not copied raw text."
  },
  {
    "id": "student-sleep-passive-risk-1",
    "source": "student_mh_en",
    "clientGroup": "student",
    "issueTags": ["depression", "sleep", "self-harm"],
    "clientUtterance": "I have not planned anything, but some mornings I wish I did not have to wake up.",
    "workerMove": "Calm suicide/self-harm safety exploration.",
    "affect": "withdrawn",
    "riskSignals": ["passive self-harm language", "sleep disruption"],
    "resistanceType": "avoidance",
    "changeTalk": [],
    "disclosureDepth": 4,
    "quality": "approved",
    "licenseNote": "Seed abstraction from student mental-health corpus pattern; not copied raw text."
  },
  {
    "id": "amod-depression-low-worth-1",
    "source": "amod",
    "clientGroup": "depression",
    "issueTags": ["depression", "self-worth", "sleep"],
    "clientUtterance": "It feels like I keep disappointing people, and sleep does not reset anything.",
    "workerMove": "Reflect low self-worth and ask what helps even a little.",
    "affect": "sad",
    "riskSignals": ["hopelessness", "sleep disruption"],
    "resistanceType": "shame",
    "changeTalk": [],
    "disclosureDepth": 2,
    "quality": "approved",
    "licenseNote": "Seed abstraction from counseling corpus pattern; not copied raw text."
  },
  {
    "id": "amod-trauma-sleep-1",
    "source": "amod",
    "clientGroup": "trauma",
    "issueTags": ["trauma", "sleep", "somatic"],
    "clientUtterance": "Sleep is the part I can talk about. The rest feels too tangled to open here.",
    "workerMove": "Offer pacing and choice about where to begin.",
    "affect": "withdrawn",
    "riskSignals": ["trauma overwhelm", "insomnia worsening"],
    "resistanceType": "avoidance",
    "changeTalk": ["wants sleep relief"],
    "disclosureDepth": 2,
    "quality": "approved",
    "licenseNote": "Seed abstraction from counseling corpus pattern; not copied raw text."
  },
  {
    "id": "amod-trauma-support-1",
    "source": "amod",
    "clientGroup": "trauma",
    "issueTags": ["trauma", "support", "self-worth"],
    "clientUtterance": "My spouse wants me to try this, but I worry I am bringing too many problems.",
    "workerMove": "Normalize complexity and identify existing support.",
    "affect": "ashamed",
    "riskSignals": ["hopelessness"],
    "resistanceType": "shame",
    "changeTalk": ["values support", "wants issues organized"],
    "disclosureDepth": 3,
    "quality": "approved",
    "licenseNote": "Seed abstraction from counseling corpus pattern; not copied raw text."
  },
  {
    "id": "therapytalk-family-invalidated-1",
    "source": "therapytalk",
    "clientGroup": "anxiety",
    "issueTags": ["anxiety", "family invalidation", "therapy access"],
    "clientUtterance": "My family says I am making it dramatic, so I start thinking maybe I should not ask for help.",
    "workerMove": "Validate help-seeking and ask who is safer to involve.",
    "affect": "anxious",
    "riskSignals": ["family coercion", "self-blame"],
    "resistanceType": "shame",
    "changeTalk": ["wants help", "wants one person to listen"],
    "disclosureDepth": 2,
    "quality": "review",
    "licenseNote": "Seed abstraction from public help-seeking pattern; no identifying details."
  },
  {
    "id": "therapytalk-panic-body-1",
    "source": "therapytalk",
    "clientGroup": "anxiety",
    "issueTags": ["anxiety", "panic", "somatic"],
    "clientUtterance": "When it happens at night my chest gets tight and I feel embarrassed even saying it out loud.",
    "workerMove": "Ask about panic pattern, supports, and immediate safety.",
    "affect": "anxious",
    "riskSignals": ["panic escalation"],
    "resistanceType": "shame",
    "changeTalk": ["wants symptoms named"],
    "disclosureDepth": 3,
    "quality": "review",
    "licenseNote": "Seed abstraction from public help-seeking pattern; no identifying details."
  },
  {
    "id": "addiction-meth-shame-1",
    "source": "addiction_sft",
    "clientGroup": "substance_use",
    "issueTags": ["meth", "shame", "relapse"],
    "clientUtterance": "I want to stop, but I already failed twice and I feel stupid saying I will try again.",
    "workerMove": "Reflect shame and separate relapse history from personal worth.",
    "affect": "ashamed",
    "riskSignals": ["relapse trigger"],
    "resistanceType": "shame",
    "changeTalk": ["desire to stop"],
    "disclosureDepth": 2,
    "quality": "review",
    "licenseNote": "Seed abstraction from addiction counseling SFT pattern; needs review before study use."
  },
  {
    "id": "addiction-meth-withdrawal-1",
    "source": "addiction_sft",
    "clientGroup": "substance_use",
    "issueTags": ["meth", "withdrawal", "support plan"],
    "clientUtterance": "Withdrawal scares me more than admitting I use. I do not know what happens if I try alone.",
    "workerMove": "Explore medical support, withdrawal risks, and safe planning.",
    "affect": "anxious",
    "riskSignals": ["withdrawal risk", "relapse trigger"],
    "resistanceType": "ambivalence",
    "changeTalk": ["wants withdrawal support", "asks for plan"],
    "disclosureDepth": 3,
    "quality": "review",
    "licenseNote": "Seed abstraction from addiction counseling SFT pattern; needs review before study use."
  },
  {
    "id": "addiction-meth-network-1",
    "source": "addiction_sft",
    "clientGroup": "substance_use",
    "issueTags": ["meth", "social network", "relapse"],
    "clientUtterance": "Most of the people who still answer my texts are the same people I use with.",
    "workerMove": "Map social supports and relapse triggers without blame.",
    "affect": "withdrawn",
    "riskSignals": ["relapse trigger", "social isolation"],
    "resistanceType": "avoidance",
    "changeTalk": ["wants different support"],
    "disclosureDepth": 4,
    "quality": "review",
    "licenseNote": "Seed abstraction from addiction counseling SFT pattern; needs review before study use."
  }
]
